{
  "metadata": {
    "title": "Kogito Status",
    "subtitle": "Kiegroup Kogito organization repositories CI status",
    "date": "2026-06-19T11:17:47.064Z",
    "createdBy": "GitHub Action",
    "createdUrl": "https://github.com/kiegroup/kogito-pipelines/actions/runs/27822529582"
  },
  "projects": [
    {
      "key": "kiegroup/kogito-pipelines",
      "name": "kogito-pipelines",
      "description": "Mirror of https://github.com/apache/incubator-kie-kogito-pipelines",
      "html_url": "https://github.com/kiegroup/kogito-pipelines",
      "updated_at": "2026-06-18T11:55:06Z",
      "homepage": "",
      "language": "Groovy",
      "default_branch": "main",
      "repo_url": "https://github.com/kiegroup/kogito-pipelines",
      "pulls_url": "https://api.github.com/repos/kiegroup/kogito-pipelines/pulls{/number}",
      "pullRequests": [
        {
          "number": 120,
          "title": "Updates actions and deps",
          "url": "https://api.github.com/repos/kiegroup/kogito-pipelines/pulls/120",
          "html_url": "https://github.com/kiegroup/kogito-pipelines/pull/120",
          "state": "open",
          "labels": [],
          "draft": false,
          "requested_reviewers": [],
          "created_at": "2026-06-18T09:09:45Z",
          "updated_at": "2026-06-18T09:09:45Z",
          "closed_at": null,
          "merged_at": null,
          "base": {
            "ref": "main",
            "sha": "c31b6cef88fd818878fa428e5f1671be12d2a818",
            "label": "kiegroup:main"
          },
          "head": {
            "ref": "updates-actions-and-deps",
            "sha": "db5c291610051037e5d2a15a97adad67802122bc",
            "label": "mareknovotny:updates-actions-and-deps"
          },
          "user": {
            "login": "mareknovotny",
            "avatar_url": "https://avatars.githubusercontent.com/u/177257?v=4",
            "html_url": "https://github.com/mareknovotny"
          },
          "checks": [
            {
              "id": 82095016266,
              "name": "Drools DSL Downstream tests - mareknovotny/drools",
              "html_url": "https://github.com/kiegroup/kogito-pipelines/actions/runs/27749161041/job/82095016266",
              "status": "completed",
              "conclusion": "failure",
              "started_at": "2026-06-18T09:12:03Z",
              "completed_at": "2026-06-18T09:13:24Z",
              "slug": "github-actions",
              "avatar_url": "https://avatars.githubusercontent.com/u/9919?v=4"
            },
            {
              "id": 82095016251,
              "name": "Drools DSL Downstream tests - mareknovotny/kie-benchmarks",
              "html_url": "https://github.com/kiegroup/kogito-pipelines/actions/runs/27749161041/job/82095016251",
              "status": "completed",
              "conclusion": "success",
              "started_at": "2026-06-18T09:12:05Z",
              "completed_at": "2026-06-18T09:13:35Z",
              "slug": "github-actions",
              "avatar_url": "https://avatars.githubusercontent.com/u/9919?v=4"
            },
            {
              "id": 82094998894,
              "name": "Kogito DSL Downstream tests - mareknovotny/kogito-pipelines",
              "html_url": "https://github.com/kiegroup/kogito-pipelines/actions/runs/27749161041/job/82094998894",
              "status": "completed",
              "conclusion": "failure",
              "started_at": "2026-06-18T09:11:57Z",
              "completed_at": "2026-06-18T09:12:33Z",
              "slug": "github-actions",
              "avatar_url": "https://avatars.githubusercontent.com/u/9919?v=4"
            },
            {
              "id": 82094998874,
              "name": "Kogito DSL Downstream tests - mareknovotny/kogito-runtimes",
              "html_url": "https://github.com/kiegroup/kogito-pipelines/actions/runs/27749161041/job/82094998874",
              "status": "completed",
              "conclusion": "failure",
              "started_at": "2026-06-18T09:11:58Z",
              "completed_at": "2026-06-18T09:12:38Z",
              "slug": "github-actions",
              "avatar_url": "https://avatars.githubusercontent.com/u/9919?v=4"
            },
            {
              "id": 82094998853,
              "name": "Kogito DSL Downstream tests - mareknovotny/kogito-apps",
              "html_url": "https://github.com/kiegroup/kogito-pipelines/actions/runs/27749161041/job/82094998853",
              "status": "completed",
              "conclusion": "failure",
              "started_at": "2026-06-18T09:11:58Z",
              "completed_at": "2026-06-18T09:12:39Z",
              "slug": "github-actions",
              "avatar_url": "https://avatars.githubusercontent.com/u/9919?v=4"
            },
            {
              "id": 82094958329,
              "name": "Get Drools DSL downstream projects",
              "html_url": "https://github.com/kiegroup/kogito-pipelines/actions/runs/27749161041/job/82094958329",
              "status": "completed",
              "conclusion": "success",
              "started_at": "2026-06-18T09:11:44Z",
              "completed_at": "2026-06-18T09:12:01Z",
              "slug": "github-actions",
              "avatar_url": "https://avatars.githubusercontent.com/u/9919?v=4"
            },
            {
              "id": 82094958325,
              "name": "dsl-tests",
              "html_url": "https://github.com/kiegroup/kogito-pipelines/actions/runs/27749161003/job/82094958325",
              "status": "completed",
              "conclusion": "success",
              "started_at": "2026-06-18T09:11:44Z",
              "completed_at": "2026-06-18T09:13:32Z",
              "slug": "github-actions",
              "avatar_url": "https://avatars.githubusercontent.com/u/9919?v=4"
            },
            {
              "id": 82094958288,
              "name": "Get Kogito DSL downstream projects",
              "html_url": "https://github.com/kiegroup/kogito-pipelines/actions/runs/27749161041/job/82094958288",
              "status": "completed",
              "conclusion": "success",
              "started_at": "2026-06-18T09:11:50Z",
              "completed_at": "2026-06-18T09:11:55Z",
              "slug": "github-actions",
              "avatar_url": "https://avatars.githubusercontent.com/u/9919?v=4"
            },
            {
              "id": 82094958254,
              "name": "Jenkinsfiles",
              "html_url": "https://github.com/kiegroup/kogito-pipelines/actions/runs/27749161003/job/82094958254",
              "status": "completed",
              "conclusion": "success",
              "started_at": "2026-06-18T09:11:44Z",
              "completed_at": "2026-06-18T09:13:27Z",
              "slug": "github-actions",
              "avatar_url": "https://avatars.githubusercontent.com/u/9919?v=4"
            }
          ]
        }
      ],
      "branchesComparison": {
        "main": {},
        " 9.10*": {}
      }
    },
    {
      "key": "kiegroup/kogito-runtimes",
      "name": "kogito-runtimes",
      "description": "This repository is a fork of apache/incubator-kie-kogito-runtimes. Please use upstream repository for development. ",
      "html_url": "https://github.com/kiegroup/kogito-runtimes",
      "updated_at": "2026-06-19T02:00:09Z",
      "homepage": "http://kogito.kie.org",
      "language": "Java",
      "default_branch": "main",
      "repo_url": "https://github.com/kiegroup/kogito-runtimes",
      "pulls_url": "https://api.github.com/repos/kiegroup/kogito-runtimes/pulls{/number}",
      "pullRequests": [
        {
          "number": 201,
          "title": "Bump actions/checkout from 6 to 7",
          "url": "https://api.github.com/repos/kiegroup/kogito-runtimes/pulls/201",
          "html_url": "https://github.com/kiegroup/kogito-runtimes/pull/201",
          "state": "open",
          "labels": [
            "dependencies",
            "github_actions"
          ],
          "draft": false,
          "requested_reviewers": [],
          "created_at": "2026-06-19T03:13:27Z",
          "updated_at": "2026-06-19T03:13:28Z",
          "closed_at": null,
          "merged_at": null,
          "base": {
            "ref": "main",
            "sha": "3e752489b75c3b495e3644229dd4991dd4152497",
            "label": "kiegroup:main"
          },
          "head": {
            "ref": "dependabot/github_actions/actions/checkout-7",
            "sha": "500f7233e31709a19c3940f9d5d461adf834f7aa",
            "label": "kiegroup:dependabot/github_actions/actions/checkout-7"
          },
          "user": {
            "login": "dependabot[bot]",
            "avatar_url": "https://avatars.githubusercontent.com/in/29110?v=4",
            "html_url": "https://github.com/apps/dependabot"
          },
          "checks": [
            {
              "id": 82277197040,
              "name": "ubuntu-latest / Java-17 / Maven-3.9.11",
              "html_url": "https://github.com/kiegroup/kogito-runtimes/actions/runs/27803079981/job/82277197040",
              "status": "completed",
              "conclusion": "success",
              "started_at": "2026-06-19T03:13:33Z",
              "completed_at": "2026-06-19T03:51:04Z",
              "slug": "github-actions",
              "avatar_url": "https://avatars.githubusercontent.com/u/9919?v=4"
            },
            {
              "id": 82277197008,
              "name": "kogito-apps (ubuntu-latest / Java-17 / Maven-3.9.11)",
              "html_url": "https://github.com/kiegroup/kogito-runtimes/actions/runs/27803079962/job/82277197008",
              "status": "completed",
              "conclusion": "success",
              "started_at": "2026-06-19T03:13:35Z",
              "completed_at": "2026-06-19T03:59:32Z",
              "slug": "github-actions",
              "avatar_url": "https://avatars.githubusercontent.com/u/9919?v=4"
            },
            {
              "id": 82277196978,
              "name": "serverless-workflow-examples (ubuntu-latest / Java-17 / Maven-3.9.11)",
              "html_url": "https://github.com/kiegroup/kogito-runtimes/actions/runs/27803079962/job/82277196978",
              "status": "completed",
              "conclusion": "success",
              "started_at": "2026-06-19T03:13:35Z",
              "completed_at": "2026-06-19T03:59:16Z",
              "slug": "github-actions",
              "avatar_url": "https://avatars.githubusercontent.com/u/9919?v=4"
            }
          ]
        }
      ],
      "branchesComparison": {
        "main": {},
        " 9.10*": {}
      }
    },
    {
      "key": "kiegroup/kogito-apps",
      "name": "kogito-apps",
      "description": "This repository is a fork of apache/incubator-kie-kogito-apps. Please use upstream repository for development. ",
      "html_url": "https://github.com/kiegroup/kogito-apps",
      "updated_at": "2026-05-26T13:53:14Z",
      "homepage": "http://kogito.kie.org",
      "language": "Java",
      "default_branch": "main",
      "repo_url": "https://github.com/kiegroup/kogito-apps",
      "pulls_url": "https://api.github.com/repos/kiegroup/kogito-apps/pulls{/number}",
      "pullRequests": [
        {
          "number": 126,
          "title": "SRVLOGIC-894: Retrying Jobs are cancelled by the periodic jobs loading",
          "url": "https://api.github.com/repos/kiegroup/kogito-apps/pulls/126",
          "html_url": "https://github.com/kiegroup/kogito-apps/pull/126",
          "state": "open",
          "labels": [],
          "draft": false,
          "requested_reviewers": [
            {
              "login": "gmunozfe",
              "avatar_url": "https://avatars.githubusercontent.com/u/1962786?v=4",
              "html_url": "https://github.com/gmunozfe"
            },
            {
              "login": "domhanak",
              "avatar_url": "https://avatars.githubusercontent.com/u/5937251?v=4",
              "html_url": "https://github.com/domhanak"
            }
          ],
          "created_at": "2026-06-19T08:54:14Z",
          "updated_at": "2026-06-19T09:04:06Z",
          "closed_at": null,
          "merged_at": null,
          "base": {
            "ref": "main",
            "sha": "d35dbffdacab98c00c28c981484649907d251963",
            "label": "kiegroup:main"
          },
          "head": {
            "ref": "SRVLOGIC-894-main",
            "sha": "f735763f5e255e6a11a9fc287048adbd04c488a5",
            "label": "wmedvede:SRVLOGIC-894-main"
          },
          "user": {
            "login": "wmedvede",
            "avatar_url": "https://avatars.githubusercontent.com/u/2431454?v=4",
            "html_url": "https://github.com/wmedvede"
          },
          "checks": [
            {
              "id": 82316752155,
              "name": "ubuntu-latest / Java-17 / Maven-3.9.11",
              "html_url": "https://github.com/kiegroup/kogito-apps/actions/runs/27815860652/job/82316752155",
              "status": "completed",
              "conclusion": "success",
              "started_at": "2026-06-19T08:54:23Z",
              "completed_at": "2026-06-19T09:40:54Z",
              "slug": "github-actions",
              "avatar_url": "https://avatars.githubusercontent.com/u/9919?v=4"
            },
            {
              "id": 82316752127,
              "name": "serverless-workflow-examples (ubuntu-latest / Java-17 / Maven-3.9.11)",
              "html_url": "https://github.com/kiegroup/kogito-apps/actions/runs/27815860684/job/82316752127",
              "status": "completed",
              "conclusion": "success",
              "started_at": "2026-06-19T08:54:23Z",
              "completed_at": "2026-06-19T09:43:10Z",
              "slug": "github-actions",
              "avatar_url": "https://avatars.githubusercontent.com/u/9919?v=4"
            }
          ]
        }
      ],
      "branchesComparison": {
        "main": {},
        " 9.10*": {}
      }
    }
  ]
}